pyhamilton/__init__.py
pyhamilton/__main__.py
pyhamilton/centrifuge_wrappers.py
pyhamilton/deckresource.py
pyhamilton/defaultcmds.py
pyhamilton/hhs_wrappers.py
pyhamilton/hig_wrappers.py
pyhamilton/interface.py
pyhamilton/liquid_handling_wrappers.py
pyhamilton/mpe_wrappers.py
pyhamilton/odtc_wrappers.py
pyhamilton/oemerr.py
pyhamilton/pH_wrappers.py
pyhamilton/paths.py
pyhamilton/util.py
pyhamilton/bin/HSLJson Library v1.6 Installer.exe
pyhamilton/bin/Hamilton HSLHttp Library Installer Version 2.7.exe
pyhamilton/bin/Hamilton MPE HSL Driver.msi
pyhamilton/bin/Hamilton pH Module v2.2.exe
pyhamilton/bin/Setup for Hamilton Centrifuge v2.0.exe
pyhamilton/library/HSLAppsLib.chm
pyhamilton/library/HSLAppsLib.chw
pyhamilton/library/HSLAppsLib.hsl
pyhamilton/library/HSLAppsLib.stp
pyhamilton/library/HSLBarcodeReader.DelComBuffer.bmp
pyhamilton/library/HSLBarcodeReader.DelComBuffer.ico
pyhamilton/library/HSLBarcodeReader.bmp
pyhamilton/library/HSLBarcodeReader.hs_
pyhamilton/library/HSLBarcodeReader.hsl
pyhamilton/library/HSLBarcodeReader.stp
pyhamilton/library/HSLBarcodeReaderEnu.chm
pyhamilton/library/HSLBarcodeReaderStringTableEnu.hs_
pyhamilton/library/HSLBarcodeReaderStringTableEnu.stp
pyhamilton/library/HSLDaisyChainCommunication.chm
pyhamilton/library/HSLDaisyChainCommunication.hsl
pyhamilton/library/HSLDaisyChainCommunication.stp
pyhamilton/library/HSLDaisyChainedMediaLine.bmp
pyhamilton/library/HSLDaisyChainedMediaLine.chm
pyhamilton/library/HSLDaisyChainedMediaLine.chw
pyhamilton/library/HSLDaisyChainedMediaLine.hsl
pyhamilton/library/HSLDaisyChainedMediaLine.stp
pyhamilton/library/HSLDaisyChainedTiltModule.chm
pyhamilton/library/HSLDaisyChainedTiltModule.chw
pyhamilton/library/HSLDaisyChainedTiltModule.hsl
pyhamilton/library/HSLDaisyChainedTiltModule.stp
pyhamilton/library/HSLTrcLib.hsl
pyhamilton/library/HSLTrcLib.stp
pyhamilton/library/HslHamHeaterShakerLib.stp
pyhamilton/library/HslHamHeaterShakerLibEnu.chw
pyhamilton-1.491.17.dist-info/LICENSE
pyhamilton-1.491.17.dist-info/METADATA
pyhamilton-1.491.17.dist-info/WHEEL
pyhamilton-1.491.17.dist-info/entry_points.txt
pyhamilton-1.491.17.dist-info/top_level.txt
pyhamilton-1.491.17.dist-info/RECORD
