Metadata-Version: 2.1
Name: pyhamilton
Version: 1.491.17
Summary: Python for Hamilton liquid handling robots
Home-page: https://github.com/dgretton/pyhamilton.git
Author: Dana Gretton
Author-email: dgretton@mit.edu
License: MIT
License-File: LICENSE
Requires-Dist: requests
Requires-Dist: pythonnet
Requires-Dist: pyserial
Requires-Dist: parse
Requires-Dist: waiter
